wmproto/__init__.py
wmproto/codec/__init__.py
wmproto/codec/built_in_json.py
wmproto/protocol.py
wmproto/sessions/ansq.py
wmproto/shared/__init__.py
wmproto/shared/dumpable.py
wmproto/shared/new_id.py
wmproto-0.1.1.dist-info/METADATA
wmproto-0.1.1.dist-info/WHEEL
wmproto-0.1.1.dist-info/RECORD
